{
  "categories": [
    {
      "id": 1,
      "title": "Anti Aging",
      "data": [
        {
          "id": 1.1,
          "title": "Laser Treatment",
          "cover": "https://diamond.talenavi.com/storage/menus/01JC2P0C49JA4EPX3N9TJ90XEA.jpg",
          "data": [
            {
              "id": 2,
              "title": "Gleaming Beauty Rejuvenation",
              "data": [
                {
                  "id": 9,
                  "type": 2,
                  "url": "https://www.youtube.com/watch?v=kd3WwUH0P0c"
                },
                {
                  "id": 1,
                  "type": 1,
                  "url": "https://diamond.talenavi.com/storage/slides/01JC2PDH91E53F2F15ZVCQVVW7.jpg"
                },
                {
                  "id": 2,
                  "type": 1,
                  "url": "https://diamond.talenavi.com/storage/slides/01JC2PE1EXP8EPHVSEQ26VHHQW.jpg"
                }
              ]
            },
            {
              "id": 3,
              "title": "Dual layer laser",
              "data": [
                {
                  "id": 3,
                  "type": 1,
                  "url": "https://diamond.talenavi.com/storage/slides/01JC2PEWBZ1XD4B2Q1KSVY723M.jpg"
                },
                {
                  "id": 4,
                  "type": 1,
                  "url": "https://diamond.talenavi.com/storage/slides/01JC2PF96S2HK7MSMV49VKWDGZ.jpg"
                }
              ]
            },
            {
              "id": 4,
              "title": "Vascular lesions",
              "data": [
                {
                  "id": 5,
                  "type": 1,
                  "url": "https://diamond.talenavi.com/storage/slides/01JC2PGWSDPXN9BPNQT215B17A.jpg"
                },
                {
                  "id": 6,
                  "type": 1,
                  "url": "https://diamond.talenavi.com/storage/slides/01JC2PHBC9X5T0M7SM38P9G9HM.jpg"
                }
              ]
            },
            {
              "id": 5,
              "title": "Lips Rejuvenation",
              "data": [
                {
                  "id": 7,
                  "type": 1,
                  "url": "https://diamond.talenavi.com/storage/slides/01JC2PHZ5137N5CT5PM8VWEZZB.jpg"
                }
              ]
            },
            {
              "id": 1,
              "title": "Cryo Treatment",
              "data": [
                {
                  "id": 8,
                  "type": 1,
                  "url": "https://diamond.talenavi.com/storage/slides/01JC2PJJ3P064YMW59P4AGXY33.jpg"
                }
              ]
            }
          ]
        }
      ]
    },
    {
      "id": 2,
      "title": "Wellness",
      "data": [
        {
          "id": 1,
          "title": "Laser Treatment 2",
          "cover": "https://diamond.talenavi.com/storage/menus/01JC2P0C49JA4EPX3N9TJ90XEA.jpg",
          "data": [
            {
              "id": 2,
              "title": "Gleaming Beauty Rejuvenation",
              "data": [
                {
                  "id": 9,
                  "type": 2,
                  "url": "https://www.youtube.com/watch?v=kd3WwUH0P0c"
                },
                {
                  "id": 1,
                  "type": 1,
                  "url": "https://diamond.talenavi.com/storage/slides/01JC2PDH91E53F2F15ZVCQVVW7.jpg"
                },
                {
                  "id": 2,
                  "type": 1,
                  "url": "https://diamond.talenavi.com/storage/slides/01JC2PE1EXP8EPHVSEQ26VHHQW.jpg"
                }
              ]
            },
            {
              "id": 3,
              "title": "Dual layer laser",
              "data": [
                {
                  "id": 3,
                  "type": 1,
                  "url": "https://diamond.talenavi.com/storage/slides/01JC2PEWBZ1XD4B2Q1KSVY723M.jpg"
                },
                {
                  "id": 4,
                  "type": 1,
                  "url": "https://diamond.talenavi.com/storage/slides/01JC2PF96S2HK7MSMV49VKWDGZ.jpg"
                }
              ]
            },
            {
              "id": 4,
              "title": "Vascular lesions",
              "data": [
                {
                  "id": 5,
                  "type": 1,
                  "url": "https://diamond.talenavi.com/storage/slides/01JC2PGWSDPXN9BPNQT215B17A.jpg"
                },
                {
                  "id": 6,
                  "type": 1,
                  "url": "https://diamond.talenavi.com/storage/slides/01JC2PHBC9X5T0M7SM38P9G9HM.jpg"
                }
              ]
            },
            {
              "id": 5,
              "title": "Lips Rejuvenation",
              "data": [
                {
                  "id": 7,
                  "type": 1,
                  "url": "https://diamond.talenavi.com/storage/slides/01JC2PHZ5137N5CT5PM8VWEZZB.jpg"
                }
              ]
            },
            {
              "id": 1,
              "title": "Cryo Treatment",
              "data": [
                {
                  "id": 8,
                  "type": 1,
                  "url": "https://diamond.talenavi.com/storage/slides/01JC2PJJ3P064YMW59P4AGXY33.jpg"
                }
              ]
            }
          ]
        }
      ]
    },
    {
      "id": 3,
      "title": "Beauty",
      "data": [
        {
          "id": 1,
          "title": "Laser Treatment 3",
          "cover": "https://diamond.talenavi.com/storage/menus/01JC2P0C49JA4EPX3N9TJ90XEA.jpg",
          "data": [
            {
              "id": 2,
              "title": "Gleaming Beauty Rejuvenation",
              "data": [
                {
                  "id": 9,
                  "type": 2,
                  "url": "https://www.youtube.com/watch?v=kd3WwUH0P0c"
                },
                {
                  "id": 1,
                  "type": 1,
                  "url": "https://diamond.talenavi.com/storage/slides/01JC2PDH91E53F2F15ZVCQVVW7.jpg"
                },
                {
                  "id": 2,
                  "type": 1,
                  "url": "https://diamond.talenavi.com/storage/slides/01JC2PE1EXP8EPHVSEQ26VHHQW.jpg"
                }
              ]
            },
            {
              "id": 3,
              "title": "Dual layer laser",
              "data": [
                {
                  "id": 3,
                  "type": 1,
                  "url": "https://diamond.talenavi.com/storage/slides/01JC2PEWBZ1XD4B2Q1KSVY723M.jpg"
                },
                {
                  "id": 4,
                  "type": 1,
                  "url": "https://diamond.talenavi.com/storage/slides/01JC2PF96S2HK7MSMV49VKWDGZ.jpg"
                }
              ]
            },
            {
              "id": 4,
              "title": "Vascular lesions",
              "data": [
                {
                  "id": 5,
                  "type": 1,
                  "url": "https://diamond.talenavi.com/storage/slides/01JC2PGWSDPXN9BPNQT215B17A.jpg"
                },
                {
                  "id": 6,
                  "type": 1,
                  "url": "https://diamond.talenavi.com/storage/slides/01JC2PHBC9X5T0M7SM38P9G9HM.jpg"
                }
              ]
            },
            {
              "id": 5,
              "title": "Lips Rejuvenation",
              "data": [
                {
                  "id": 7,
                  "type": 1,
                  "url": "https://diamond.talenavi.com/storage/slides/01JC2PHZ5137N5CT5PM8VWEZZB.jpg"
                }
              ]
            },
            {
              "id": 1,
              "title": "Cryo Treatment",
              "data": [
                {
                  "id": 8,
                  "type": 1,
                  "url": "https://diamond.talenavi.com/storage/slides/01JC2PJJ3P064YMW59P4AGXY33.jpg"
                }
              ]
            }
          ]
        }
      ]
    },
    {
      "id": 4,
      "title": "Certifications",
      "data": [
        {
          "id": 1,
          "title": "Laser Treatment 4",
          "cover": "https://diamond.talenavi.com/storage/menus/01JC2P0C49JA4EPX3N9TJ90XEA.jpg",
          "data": [
            {
              "id": 2,
              "title": "Gleaming Beauty Rejuvenation",
              "data": [
                {
                  "id": 9,
                  "type": 2,
                  "url": "https://www.youtube.com/watch?v=kd3WwUH0P0c"
                },
                {
                  "id": 1,
                  "type": 1,
                  "url": "https://diamond.talenavi.com/storage/slides/01JC2PDH91E53F2F15ZVCQVVW7.jpg"
                },
                {
                  "id": 2,
                  "type": 1,
                  "url": "https://diamond.talenavi.com/storage/slides/01JC2PE1EXP8EPHVSEQ26VHHQW.jpg"
                }
              ]
            },
            {
              "id": 3,
              "title": "Dual layer laser",
              "data": [
                {
                  "id": 3,
                  "type": 1,
                  "url": "https://diamond.talenavi.com/storage/slides/01JC2PEWBZ1XD4B2Q1KSVY723M.jpg"
                },
                {
                  "id": 4,
                  "type": 1,
                  "url": "https://diamond.talenavi.com/storage/slides/01JC2PF96S2HK7MSMV49VKWDGZ.jpg"
                }
              ]
            },
            {
              "id": 4,
              "title": "Vascular lesions",
              "data": [
                {
                  "id": 5,
                  "type": 1,
                  "url": "https://diamond.talenavi.com/storage/slides/01JC2PGWSDPXN9BPNQT215B17A.jpg"
                },
                {
                  "id": 6,
                  "type": 1,
                  "url": "https://diamond.talenavi.com/storage/slides/01JC2PHBC9X5T0M7SM38P9G9HM.jpg"
                }
              ]
            },
            {
              "id": 5,
              "title": "Lips Rejuvenation",
              "data": [
                {
                  "id": 7,
                  "type": 1,
                  "url": "https://diamond.talenavi.com/storage/slides/01JC2PHZ5137N5CT5PM8VWEZZB.jpg"
                }
              ]
            },
            {
              "id": 1,
              "title": "Cryo Treatment",
              "data": [
                {
                  "id": 8,
                  "type": 1,
                  "url": "https://diamond.talenavi.com/storage/slides/01JC2PJJ3P064YMW59P4AGXY33.jpg"
                }
              ]
            }
          ]
        }
      ]
    }
  ]
}
